sdk/__init__.py
sdk/run.py
sdk/test_hander_perf.py
sdk/apis/__init__.py
sdk/apis/build.py
sdk/apis/client.py
sdk/apis/pdu.py
sdk/apis/perf.py
sdk/apis/pr.py
sdk/config/__init__.py
sdk/config/develop.py
sdk/config/prod.py
sdk/handles/__init__.py
sdk/handles/build.py
sdk/handles/pdu.py
sdk/handles/perf.py
sdk/handles/pr.py
sdk/schemas/__init__.py
sdk/schemas/jenkins.py
sdk/schemas/pull_request.py
sdk/schemas/pull_request_job.py
sdk/schemas/test_case.py
sdk/utils/__init__.py
sdk/utils/csv_utils.py
sdk/utils/file_utils.py
sdk/utils/json_utils.py
sdk/utils/pd_utils.py
sdk/utils/xml_utils.py
birenci_infra-0.0.9.dist-info/METADATA
birenci_infra-0.0.9.dist-info/WHEEL
birenci_infra-0.0.9.dist-info/top_level.txt
birenci_infra-0.0.9.dist-info/RECORD
