Metadata-Version: 2.1
Name: birenci-infra
Version: 0.0.9
Summary: biren ci sdk
Home-page: https://gitlab.birentech.com/software/br_ci_db
Author: br_infra
Author-email: br_infra@birentech.com
License: UNKNOWN
Platform: UNKNOWN
Classifier: Programming Language :: Python :: 3
Classifier: License :: OSI Approved :: MIT License
Classifier: Operating System :: OS Independent
Requires-Python: >=3.6
